bio2bel_mirtarbase/__init__.py
bio2bel_mirtarbase/__main__.py
bio2bel_mirtarbase/cli.py
bio2bel_mirtarbase/constants.py
bio2bel_mirtarbase/enrich.py
bio2bel_mirtarbase/manager.py
bio2bel_mirtarbase/models.py
bio2bel_mirtarbase/parser.py
bio2bel_mirtarbase/utils.py
bio2bel_mirtarbase/web.py
bio2bel_mirtarbase-0.2.2.dist-info/LICENSE
bio2bel_mirtarbase-0.2.2.dist-info/METADATA
bio2bel_mirtarbase-0.2.2.dist-info/WHEEL
bio2bel_mirtarbase-0.2.2.dist-info/entry_points.txt
bio2bel_mirtarbase-0.2.2.dist-info/top_level.txt
bio2bel_mirtarbase-0.2.2.dist-info/RECORD
