Metadata-Version: 2.1
Name: bio2bel-mirtarbase
Version: 0.2.2
Summary: A package for converting miRTarBase to BEL
Home-page: https://github.com/bio2bel/mirtarbase
Author: Charles Tapley Hoyt and Colin Birkenbihl
Author-email: charles.hoyt@scai.fraunhofer.de
Maintainer: Charles Tapley Hoyt and Colin Birkenbihl
Maintainer-email: charles.hoyt@scai.fraunhofer.de
License: MIT License
Keywords: Biological Expression Language,Micro-RNA,Systems Biology,Networks Biology
Platform: UNKNOWN
Classifier: Development Status :: 4 - Beta
Classifier: Environment :: Console
Classifier: Intended Audience :: Developers
Classifier: Intended Audience :: Science/Research
Classifier: Operating System :: OS Independent
Classifier: Programming Language :: Python
Classifier: Programming Language :: Python :: 3 :: Only
Classifier: Programming Language :: Python :: 3.6
Classifier: Programming Language :: Python :: 3.7
Classifier: Topic :: Scientific/Engineering :: Bio-Informatics
Classifier: License :: OSI Approved :: MIT License
Requires-Dist: pybel (>=0.13.0)
Requires-Dist: bio2bel (<0.3.0,>=0.2.0)
Requires-Dist: bio2bel-hgnc (>=0.2.3)
Requires-Dist: bio2bel-entrez (>=0.2.1)
Requires-Dist: bio2bel-mirbase (>=0.1.1)
Requires-Dist: pandas
Requires-Dist: sqlalchemy
Requires-Dist: xlrd
Requires-Dist: click
Requires-Dist: tqdm
Provides-Extra: docs
Requires-Dist: flask ; extra == 'docs'
Requires-Dist: flask-admin ; extra == 'docs'
Requires-Dist: sphinx ; extra == 'docs'
Requires-Dist: sphinx-rtd-theme ; extra == 'docs'
Requires-Dist: sphinx-click ; extra == 'docs'
Requires-Dist: sphinx-autodoc-typehints ; extra == 'docs'
Provides-Extra: web
Requires-Dist: flask ; extra == 'web'
Requires-Dist: flask-admin ; extra == 'web'
